uidriver/__init__.py
az_uidriver-0.0.1.dist-info/METADATA
az_uidriver-0.0.1.dist-info/WHEEL
az_uidriver-0.0.1.dist-info/RECORD
